Seizure_TimeFreqROI_Annotator/__init__.py
Seizure_TimeFreqROI_Annotator/annotator/__init__.py
Seizure_TimeFreqROI_Annotator/annotator/core.py
Seizure_TimeFreqROI_Annotator/annotator/gui.py
Seizure_TimeFreqROI_Annotator/datasets/__init__.py
Seizure_TimeFreqROI_Annotator/datasets/base.py
Seizure_TimeFreqROI_Annotator/datasets/seizure_spectrograms.py
Seizure_TimeFreqROI_Annotator/datasets/utils.py
seizure_timefreqroi_annotator-0.1.0.dist-info/METADATA
seizure_timefreqroi_annotator-0.1.0.dist-info/WHEEL
seizure_timefreqroi_annotator-0.1.0.dist-info/top_level.txt
seizure_timefreqroi_annotator-0.1.0.dist-info/RECORD
